NEST/NEST.py
NEST/__init__.py
NEST/domain.pkl
NEST/tutorial.ipynb
NEST/models/BaSTI.sav
NEST/models/BaSTI2.sav
NEST/models/BaSTI2_BPRP.sav
NEST/models/BaSTI_BPRP.sav
NEST/models/Dartmouth.sav
NEST/models/Dartmouth_BPRP.sav
NEST/models/MIST.sav
NEST/models/MIST_BPRP.sav
NEST/models/NN_BaSTI.json
NEST/models/NN_BaSTI.sav
NEST/models/NN_BaSTI.sav.old
NEST/models/NN_BaSTI_BPRP.json
NEST/models/NN_BaSTI_BPRP.sav
NEST/models/NN_BaSTI_HST_BPRP.json
NEST/models/NN_BaSTI_HST_BPRP.sav
NEST/models/NN_BaSTI_HST_alpha_zero_BPRP.json
NEST/models/NN_BaSTI_HST_alpha_zero_BPRP.sav
NEST/models/NN_BaSTI_cut.json
NEST/models/NN_BaSTI_cut.sav
NEST/models/NN_BaSTI_cut_BPRP.json
NEST/models/NN_BaSTI_cut_BPRP.sav
NEST/models/NN_Dartmouth.json
NEST/models/NN_Dartmouth.sav
NEST/models/NN_Dartmouth_BPRP.json
NEST/models/NN_Dartmouth_BPRP.sav
NEST/models/NN_MIST.json
NEST/models/NN_MIST.sav
NEST/models/NN_MIST_BPRP.json
NEST/models/NN_MIST_BPRP.sav
NEST/models/NN_PARSEC.json
NEST/models/NN_PARSEC.sav
NEST/models/NN_PARSEC_BPRP.json
NEST/models/NN_PARSEC_BPRP.sav
NEST/models/NN_SYCLIST.json
NEST/models/NN_SYCLIST.sav
NEST/models/NN_SYCLIST_BPRP.json
NEST/models/NN_SYCLIST_BPRP.sav
NEST/models/NN_YaPSI.json
NEST/models/NN_YaPSI.sav
NEST/models/NN_YaPSI_BPRP.json
NEST/models/NN_YaPSI_BPRP.sav
NEST/models/PARSEC.sav
NEST/models/PARSEC_BPRP.sav
NEST/models/SYCLIST.sav
NEST/models/SYCLIST_BPRP.sav
NEST/models/YaPSI.sav
NEST/models/YaPSI_BPRP.sav
NEST/models/scaler_BaSTI.sav
NEST/models/scaler_BaSTI_BPRP.sav
NEST/models/scaler_BaSTI_BPRP_cut.sav
NEST/models/scaler_BaSTI_HST_BPRP.sav
NEST/models/scaler_BaSTI_HST_alpha_zero_BPRP.sav
NEST/models/scaler_BaSTI_cut.sav
NEST/models/scaler_BaSTI_cut_BPRP.sav
NEST/models/scaler_Dartmouth.sav
NEST/models/scaler_Dartmouth_BPRP.sav
NEST/models/scaler_MIST.sav
NEST/models/scaler_MIST_BPRP.sav
NEST/models/scaler_PARSEC.sav
NEST/models/scaler_PARSEC_BPRP.sav
NEST/models/scaler_SYCLIST.sav
NEST/models/scaler_SYCLIST_BPRP.sav
NEST/models/scaler_YaPSI.sav
nest_ages-0.5.0.dist-info/METADATA
nest_ages-0.5.0.dist-info/WHEEL
nest_ages-0.5.0.dist-info/top_level.txt
nest_ages-0.5.0.dist-info/RECORD
