Metadata-Version: 2.4
Name: nest-ages
Version: 0.5.0
Summary: A python package that provides neural networks to estimate ages of stars/star populations.
Author-email: Tristan Boin <tristan.boin@gmail.com>
License-Expression: MIT
Project-URL: Homepage, https://star-age.github.io/NEST-docs/
Classifier: Programming Language :: Python :: 3
Classifier: Operating System :: OS Independent
